LICENSE
MANIFEST.in
README.md
setup.py
testingbatesterwithpython/__init__.py
testingbatesterwithpython/api_helper.py
testingbatesterwithpython/configuration.py
testingbatesterwithpython/decorators.py
testingbatesterwithpython/testingbatesterwithpython_client.py
testingbatesterwithpython.egg-info/PKG-INFO
testingbatesterwithpython.egg-info/SOURCES.txt
testingbatesterwithpython.egg-info/dependency_links.txt
testingbatesterwithpython.egg-info/requires.txt
testingbatesterwithpython.egg-info/top_level.txt
testingbatesterwithpython/controllers/__init__.py
testingbatesterwithpython/controllers/api_controller.py
testingbatesterwithpython/controllers/base_controller.py
testingbatesterwithpython/exceptions/__init__.py
testingbatesterwithpython/exceptions/api_exception.py
testingbatesterwithpython/http/__init__.py
testingbatesterwithpython/http/http_call_back.py
testingbatesterwithpython/http/http_client.py
testingbatesterwithpython/http/http_context.py
testingbatesterwithpython/http/http_method_enum.py
testingbatesterwithpython/http/http_request.py
testingbatesterwithpython/http/http_response.py
testingbatesterwithpython/http/requests_client.py
testingbatesterwithpython/http/auth/__init__.py
testingbatesterwithpython/http/auth/basic_auth.py
testingbatesterwithpython/models/__init__.py
testingbatesterwithpython/models/suite_code_enum.py
tests/__init__.py
tests/http_response_catcher.py
tests/test_helper.py
tests/controllers/__init__.py
tests/controllers/controller_test_base.py
tests/controllers/test_api_controller.py